splurge_dsv/__init__.py
splurge_dsv/__main__.py
splurge_dsv/cli.py
splurge_dsv/dsv.py
splurge_dsv/dsv_config.py
splurge_dsv/dsv_helper.py
splurge_dsv/exceptions.py
splurge_dsv/string_tokenizer.py
splurge_dsv/_vendor/splurge_exceptions/__init__.py
splurge_dsv/_vendor/splurge_exceptions/__main__.py
splurge_dsv/_vendor/splurge_exceptions/cli.py
splurge_dsv/_vendor/splurge_exceptions/core/__init__.py
splurge_dsv/_vendor/splurge_exceptions/core/base.py
splurge_dsv/_vendor/splurge_exceptions/core/exceptions.py
splurge_dsv/_vendor/splurge_exceptions/formatting/__init__.py
splurge_dsv/_vendor/splurge_exceptions/formatting/message.py
splurge_dsv/_vendor/splurge_pub_sub/__init__.py
splurge_dsv/_vendor/splurge_pub_sub/__main__.py
splurge_dsv/_vendor/splurge_pub_sub/cli.py
splurge_dsv/_vendor/splurge_pub_sub/constants.py
splurge_dsv/_vendor/splurge_pub_sub/decorators.py
splurge_dsv/_vendor/splurge_pub_sub/errors.py
splurge_dsv/_vendor/splurge_pub_sub/exceptions.py
splurge_dsv/_vendor/splurge_pub_sub/filters.py
splurge_dsv/_vendor/splurge_pub_sub/message.py
splurge_dsv/_vendor/splurge_pub_sub/pubsub.py
splurge_dsv/_vendor/splurge_pub_sub/pubsub_aggregator.py
splurge_dsv/_vendor/splurge_pub_sub/pubsub_solo.py
splurge_dsv/_vendor/splurge_pub_sub/types.py
splurge_dsv/_vendor/splurge_pub_sub/utility.py
splurge_dsv/_vendor/splurge_pub_sub/_vendor/splurge_exceptions/__init__.py
splurge_dsv/_vendor/splurge_pub_sub/_vendor/splurge_exceptions/__main__.py
splurge_dsv/_vendor/splurge_pub_sub/_vendor/splurge_exceptions/cli.py
splurge_dsv/_vendor/splurge_pub_sub/_vendor/splurge_exceptions/core/__init__.py
splurge_dsv/_vendor/splurge_pub_sub/_vendor/splurge_exceptions/core/base.py
splurge_dsv/_vendor/splurge_pub_sub/_vendor/splurge_exceptions/core/exceptions.py
splurge_dsv/_vendor/splurge_pub_sub/_vendor/splurge_exceptions/formatting/__init__.py
splurge_dsv/_vendor/splurge_pub_sub/_vendor/splurge_exceptions/formatting/message.py
splurge_dsv/_vendor/splurge_safe_io/__init__.py
splurge_dsv-2025.6.0.dist-info/licenses/LICENSE
splurge_dsv-2025.6.0.dist-info/METADATA
splurge_dsv-2025.6.0.dist-info/WHEEL
splurge_dsv-2025.6.0.dist-info/entry_points.txt
splurge_dsv-2025.6.0.dist-info/top_level.txt
splurge_dsv-2025.6.0.dist-info/RECORD
