Metadata-Version: 2.4
Name: splurge-dsv
Version: 2025.6.0
Summary: A utility library for working with DSV (Delimited String Values) files
Author: Jim Schilling
License-Expression: MIT
Project-URL: Homepage, https://github.com/jim-schilling/splurge-dsv
Project-URL: Repository, https://github.com/jim-schilling/splurge-dsv
Project-URL: Documentation, https://github.com/jim-schilling/splurge-dsv#readme
Project-URL: Bug Tracker, https://github.com/jim-schilling/splurge-dsv/issues
Keywords: dsv,csv,tsv,delimited,parsing,file-processing
Classifier: Development Status :: 4 - Beta
Classifier: Intended Audience :: Developers
Classifier: Programming Language :: Python :: 3
Classifier: Programming Language :: Python :: 3.10
Classifier: Programming Language :: Python :: 3.11
Classifier: Programming Language :: Python :: 3.12
Classifier: Programming Language :: Python :: 3.13
Classifier: Topic :: Software Development :: Libraries :: Python Modules
Classifier: Topic :: Text Processing :: Filters
Requires-Python: >=3.10
License-File: LICENSE
Requires-Dist: PyYAML>=6.0
Provides-Extra: dev
Requires-Dist: pytest>=7.0.0; extra == "dev"
Requires-Dist: pytest-cov>=4.0.0; extra == "dev"
Requires-Dist: mypy>=1.0.0; extra == "dev"
Requires-Dist: ruff>=0.0.241; extra == "dev"
Requires-Dist: pytest-mock>=3.0.0; extra == "dev"
Requires-Dist: hypothesis>=6.0.0; extra == "dev"
Requires-Dist: pre-commit>=4.3.0; extra == "dev"
Dynamic: license-file
